things3_mcp/__init__.py
things3_mcp/applescript_bridge.py
things3_mcp/date_converter.py
things3_mcp/fast_server.py
things3_mcp/formatters.py
things3_mcp/logging_config.py
things3_mcp_server-2.0.6.dist-info/METADATA
things3_mcp_server-2.0.6.dist-info/WHEEL
things3_mcp_server-2.0.6.dist-info/entry_points.txt
things3_mcp_server-2.0.6.dist-info/licenses/LICENSE
things3_mcp_server-2.0.6.dist-info/RECORD
