Metadata-Version: 2.4
Name: Things3-MCP-server
Version: 2.0.6
Summary: MCP server for Things 3 with read/write support for tasks, projects, areas and tags.
Project-URL: Homepage, https://github.com/rossshannon/things-fastmcp
Project-URL: Bug Tracker, https://github.com/rossshannon/things-fastmcp/issues
Project-URL: Documentation, https://github.com/rossshannon/things-fastmcp#readme
Author-email: Ross Shannon <4503044+rossshannon@users.noreply.github.com>, Yaroslav Krempovych <51231325+excelsior@users.noreply.github.com>, Harald Lindstrøm <hald@users.noreply.github.com>
License: MIT License
License-File: LICENSE
Keywords: anthropic,apple,claude,fastmcp,macos,mcp,productivity,task-management,things,things3
Classifier: Development Status :: 5 - Production/Stable
Classifier: Intended Audience :: End Users/Desktop
Classifier: License :: OSI Approved :: MIT License
Classifier: Operating System :: MacOS
Classifier: Programming Language :: Python :: 3.12
Classifier: Topic :: Office/Business :: Scheduling
Classifier: Topic :: Software Development :: Libraries :: Python Modules
Classifier: Topic :: Utilities
Requires-Python: >=3.12
Requires-Dist: httpx>=0.28.1
Requires-Dist: mcp[cli]>=1.2.0
Requires-Dist: things-py>=0.0.15
Provides-Extra: dev
Requires-Dist: bandit[toml]>=1.8.6; extra == 'dev'
Requires-Dist: build>=0.10.0; extra == 'dev'
Requires-Dist: mypy>=1.17.0; extra == 'dev'
Requires-Dist: pre-commit>=4.2.0; extra == 'dev'
Requires-Dist: pytest-cov>=6.2.1; extra == 'dev'
Requires-Dist: pytest-html>=4.1.1; extra == 'dev'
Requires-Dist: pytest-timeout>=2.3.1; extra == 'dev'
Requires-Dist: pytest>=8.4.1; extra == 'dev'
Requires-Dist: ruff>=0.12.3; extra == 'dev'
Requires-Dist: safety>=3.6.0; extra == 'dev'
Requires-Dist: twine>=4.0.0; extra == 'dev'
